Workbook

Sheet Summary
C2: KOVAI KONGU MESS (FIRST FLOOR) | U2: KOVAI KONGU MESS (GROUND FLOOR)
A3: Date | B3: Day | C3: CASH | D3: Expenses | E3: PAYTM | F3: Phonepe | G3: Swiggy | H3: N. Swiggy | I3: Zomato | J3: N. Zomato | K3: Ownly | L3: Swayo | M3: MP | N3: Credit | O3: Day Total | P3: Grand Total | Q3: Sales | R3: Adv. / Misc. | S3: Differ. | U3: CASH | V3: Expenses | W3: PAYTM | X3: Phonepe | Y3: Swiggy | Z3: Zomato | AA3: GF | AB3: MP | AC3: YH | AD3: Credit | AE3: Total | AF3: Sales | AG3: Adv. / Misc. | AH3: Differ
A4: 46266 | B4: Tue | O4: =P4-H4-J4 -> 0 | P4: =SUM(C4:N4) -> 0 | S4: =P4-Q4-R4 -> 0 | AE4: =SUM(U4:AD4) -> 0 | AG4: 0 | AH4: =AE4-AF4 -> 0
A5: 46267 | B5: Wed | O5: =P5-H5-J5 -> 0 | P5: =SUM(C5:N5) -> 0 | S5: =P5-Q5-R5 -> 0 | AE5: =SUM(U5:AD5) -> 0 | AG5: 0 | AH5: =AE5-AF5 -> 0
A6: 46268 | B6: Thu | O6: =P6-H6-J6 -> 0 | P6: =SUM(C6:N6) -> 0 | S6: =P6-Q6-R6 -> 0 | AE6: =SUM(U6:AD6) -> 0 | AG6: 0 | AH6: =AE6-AF6 -> 0
A7: 46269 | B7: Fri | O7: =P7-H7-J7 -> 0 | P7: =SUM(C7:N7) -> 0 | S7: =P7-Q7-R7 -> 0 | AE7: =SUM(U7:AD7) -> 0 | AG7: 0 | AH7: =AE7-AF7 -> 0
A8: 46270 | B8: Sat | O8: =P8-H8-J8 -> 0 | P8: =SUM(C8:N8) -> 0 | S8: =P8-Q8-R8 -> 0 | AE8: =SUM(U8:AD8) -> 0 | AG8: 0 | AH8: =AE8-AF8 -> 0
A9: 46271 | B9: Sun | O9: =P9-H9-J9 -> 0 | P9: =SUM(C9:N9) -> 0 | S9: =P9-Q9-R9 -> 0 | AE9: =SUM(U9:AD9) -> 0 | AG9: 0 | AH9: =AE9-AF9 -> 0
A10: 46272 | B10: Mon | O10: =P10-H10-J10 -> 0 | P10: =SUM(C10:N10) -> 0 | S10: =P10-Q10-R10 -> 0 | AE10: =SUM(U10:AD10) -> 0 | AG10: 0 | AH10: =AE10-AF10 -> 0
A11: 46273 | B11: Tue | O11: =P11-H11-J11 -> 0 | P11: =SUM(C11:N11) -> 0 | S11: =P11-Q11-R11 -> 0 | AE11: =SUM(U11:AD11) -> 0 | AG11: 0 | AH11: =AE11-AF11 -> 0
A12: 46274 | B12: Wed | O12: =P12-H12-J12 -> 0 | P12: =SUM(C12:N12) -> 0 | S12: =P12-Q12-R12 -> 0 | AE12: =SUM(U12:AD12) -> 0 | AG12: 0 | AH12: =AE12-AF12 -> 0
A13: 46275 | B13: Thu | O13: =P13-H13-J13 -> 0 | P13: =SUM(C13:N13) -> 0 | S13: =P13-Q13-R13 -> 0 | AE13: =SUM(U13:AD13) -> 0 | AG13: 0 | AH13: =AE13-AF13 -> 0
A14: 46276 | B14: Fri | O14: =P14-H14-J14 -> 0 | P14: =SUM(C14:N14) -> 0 | S14: =P14-Q14-R14 -> 0 | AE14: =SUM(U14:AD14) -> 0 | AG14: 0 | AH14: =AE14-AF14 -> 0
A15: 46277 | B15: Sat | O15: =P15-H15-J15 -> 0 | P15: =SUM(C15:N15) -> 0 | S15: =P15-Q15-R15 -> 0 | AE15: =SUM(U15:AD15) -> 0 | AG15: 0 | AH15: =AE15-AF15 -> 0
... A33: 46295 | B33: Wed | O33: =P33-H33-J33 -> 0 | P33: =SUM(C33:N33) -> 0 | S33: =P33-Q33-R33 -> 0 | AE33: =SUM(U33:AD33) -> 0 | AG33: 0 | AH33: =AE33-AF33 -> 0
O34: =P34-H34-J34 -> 0 | P34: =SUM(C34:N34) -> 0 | S34: =P34-Q34-R34 -> 0 | AE34: =SUM(U34:AD34) -> 0 | AG34: 0 | AH34: =AE34-AF34 -> 0
C37: =SUM(C4:C34) -> 0 | D37: =SUM(D4:D34) -> 0 | E37: =SUM(E4:E34) -> 0 | F37: =SUM(F4:F34) -> 0 | G37: =SUM(G4:G34) -> 0 | H37: =SUM(H4:H34) -> 0 | I37: =SUM(I4:I34) -> 0 | J37: =SUM(J4:J34) -> 0 | ... S37: =SUM(S4:S34) -> 0 | U37: =SUM(U4:U34) -> 0 | V37: =SUM(V4:V34) -> 0 | W37: =SUM(W4:W34) -> 0 | X37: =SUM(X4:X34) -> 0 | Y37: =SUM(Y4:Y34) -> 0 | Z37: =SUM(Z4:Z34) -> 0 | AA37: =SUM(AA4:AA34) -> 0 | AB37: =SUM(AB4:AB34) -> 0 | AD37: =SUM(AD4:AD34) -> 0 | AE37: =SUM(AE4:AE34) -> 0 | AF37: =SUM(AF4:AF34) -> 0 | AG37: =SUM(AG4:AG34) -> 0 | AH37: =SUM(AH4:AH34) -> 0
O40: Avg/Day | Q40: =+Q37/20 -> 0 | AF40: =AF37/20 -> 0
AB41: Total Petpooja Sales | AF41: =Q37+AF37 -> 0
AB43: Avg. Per Day | AF43: =+AF41/20 -> 0
AB45: Approx. Projection for Sep'2026 | AF45: =AF43*30 -> 0

Sheet Paytm
A1: Date | B1: Day | C1: KKM (F.F) | D1: KKM (G.F) | E1: Total | F1: Credited in Bank | G1: Commission / Charges | H1: %
A2: 46266 | B2: Tue | C2: =Summary!E4 -> 0 | D2: =Summary!W4 -> 0 | E2: =C2+D2 -> 0 | G2: =E2-F2 -> 0 | H2: =G2/E2 -> #DIV/0!
A3: 46267 | B3: Wed | C3: =Summary!E5 -> 0 | D3: =Summary!W5 -> 0 | E3: =C3+D3 -> 0 | G3: =E3-F3 -> 0 | H3: =G3/E3 -> #DIV/0!
A4: 46268 | B4: Thu | C4: =Summary!E6 -> 0 | D4: =Summary!W6 -> 0 | E4: =C4+D4 -> 0 | G4: =E4-F4 -> 0 | H4: =G4/E4 -> #DIV/0!
A5: 46269 | B5: Fri | C5: =Summary!E7 -> 0 | D5: =Summary!W7 -> 0 | E5: =C5+D5 -> 0 | G5: =E5-F5 -> 0 | H5: =G5/E5 -> #DIV/0!
A6: 46270 | B6: Sat | C6: =Summary!E8 -> 0 | D6: =Summary!W8 -> 0 | E6: =C6+D6 -> 0 | G6: =E6-F6 -> 0 | H6: =G6/E6 -> #DIV/0!
A7: 46271 | B7: Sun | C7: =Summary!E9 -> 0 | D7: =Summary!W9 -> 0 | E7: =C7+D7 -> 0 | G7: =E7-F7 -> 0 | H7: =G7/E7 -> #DIV/0!
A8: 46272 | B8: Mon | C8: =Summary!E10 -> 0 | D8: =Summary!W10 -> 0 | E8: =C8+D8 -> 0 | G8: =E8-F8 -> 0 | H8: =G8/E8 -> #DIV/0!
A9: 46273 | B9: Tue | C9: =Summary!E11 -> 0 | D9: =Summary!W11 -> 0 | E9: =C9+D9 -> 0 | G9: =E9-F9 -> 0 | H9: =G9/E9 -> #DIV/0!
A10: 46274 | B10: Wed | C10: =Summary!E12 -> 0 | D10: =Summary!W12 -> 0 | E10: =C10+D10 -> 0 | G10: =E10-F10 -> 0 | H10: =G10/E10 -> #DIV/0!
A11: 46275 | B11: Thu | C11: =Summary!E13 -> 0 | D11: =Summary!W13 -> 0 | E11: =C11+D11 -> 0 | G11: =E11-F11 -> 0 | H11: =G11/E11 -> #DIV/0!
A12: 46276 | B12: Fri | C12: =Summary!E14 -> 0 | D12: =Summary!W14 -> 0 | E12: =C12+D12 -> 0 | G12: =E12-F12 -> 0 | H12: =G12/E12 -> #DIV/0!
A13: 46277 | B13: Sat | C13: =Summary!E15 -> 0 | D13: =Summary!W15 -> 0 | E13: =C13+D13 -> 0 | G13: =E13-F13 -> 0 | H13: =G13/E13 -> #DIV/0!
... A32: 46265 | B32: Mon | C32: =Summary!E34 -> 0 | D32: =Summary!W34 -> 0 | E32: =C32+D32 -> 0 | G32: =E32-F32 -> 0 | H32: =G32/E32 -> #DIV/0!
C34: =SUM(C2:C33) -> 0 | D34: =SUM(D2:D33) -> 0 | E34: =SUM(E2:E33) -> 0 | F34: =SUM(F2:F33) -> 0 | G34: =SUM(G2:G33) -> 0 | H34: =SUM(H2:H33) -> #DIV/0!

Sheet Phone pe
A1: Date | B1: Day | C1: KKM (F.F) | D1: KKM (G.F) | E1: Total | F1: Credited in Bank | G1: Commission / Charges | H1: %
A2: 46266 | B2: Tue | C2: =Summary!F4 -> 0 | D2: =Summary!X4 -> 0 | E2: =C2+D2 -> 0 | G2: =E2-F2 -> 0 | H2: =G2/E2 -> #DIV/0!
A3: 46267 | B3: Wed | C3: =Summary!F5 -> 0 | D3: =Summary!X5 -> 0 | E3: =C3+D3 -> 0 | G3: =E3-F3 -> 0 | H3: =G3/E3 -> #DIV/0!
A4: 46268 | B4: Thu | C4: =Summary!F6 -> 0 | D4: =Summary!X6 -> 0 | E4: =C4+D4 -> 0 | G4: =E4-F4 -> 0 | H4: =G4/E4 -> #DIV/0!
A5: 46269 | B5: Fri | C5: =Summary!F7 -> 0 | D5: =Summary!X7 -> 0 | E5: =C5+D5 -> 0 | G5: =E5-F5 -> 0 | H5: =G5/E5 -> #DIV/0!
A6: 46270 | B6: Sat | C6: =Summary!F8 -> 0 | D6: =Summary!X8 -> 0 | E6: =C6+D6 -> 0 | G6: =E6-F6 -> 0 | H6: =G6/E6 -> #DIV/0!
A7: 46271 | B7: Sun | C7: =Summary!F9 -> 0 | D7: =Summary!X9 -> 0 | E7: =C7+D7 -> 0 | G7: =E7-F7 -> 0 | H7: =G7/E7 -> #DIV/0!
A8: 46272 | B8: Mon | C8: =Summary!F10 -> 0 | D8: =Summary!X10 -> 0 | E8: =C8+D8 -> 0 | G8: =E8-F8 -> 0 | H8: =G8/E8 -> #DIV/0!
A9: 46273 | B9: Tue | C9: =Summary!F11 -> 0 | D9: =Summary!X11 -> 0 | E9: =C9+D9 -> 0 | G9: =E9-F9 -> 0 | H9: =G9/E9 -> #DIV/0!
A10: 46274 | B10: Wed | C10: =Summary!F12 -> 0 | D10: =Summary!X12 -> 0 | E10: =C10+D10 -> 0 | G10: =E10-F10 -> 0 | H10: =G10/E10 -> #DIV/0!
A11: 46275 | B11: Thu | C11: =Summary!F13 -> 0 | D11: =Summary!X13 -> 0 | E11: =C11+D11 -> 0 | G11: =E11-F11 -> 0 | H11: =G11/E11 -> #DIV/0!
A12: 46276 | B12: Fri | C12: =Summary!F14 -> 0 | D12: =Summary!X14 -> 0 | E12: =C12+D12 -> 0 | G12: =E12-F12 -> 0 | H12: =G12/E12 -> #DIV/0!
A13: 46277 | B13: Sat | C13: =Summary!F15 -> 0 | D13: =Summary!X15 -> 0 | E13: =C13+D13 -> 0 | G13: =E13-F13 -> 0 | H13: =G13/E13 -> #DIV/0!
... A32: 46265 | B32: Mon | C32: =Summary!F34 -> 0 | D32: =Summary!X34 -> 0 | E32: =C32+D32 -> 0 | G32: =E32-F32 -> 0 | H32: =G32/E32 -> #DIV/0!

Sheet Cash
A1: Date | B1: Day | C1: KKM(F.F) Net Cash | D1: KKM (G.F) Net Cash | E1: Party Order Income | F1: Rare/ Spl Cash Exps. | G1: Total Cash to Deposit | H1: Deposited in Bank | I1: Running Bal to Deposit
A2: 46266 | B2: Tue | C2: =Summary!C4 -> 0 | D2: =Summary!U4 -> 0 | E2: 0 | F2: 0 | G2: =C2+D2 -> 0 | I2: =0+G2 -> 0
A3: 46267 | B3: Wed | C3: =Summary!C5 -> 0 | D3: =Summary!U5 -> 0 | G3: =C3+D3 -> 0 | I3: =I2+G3+E3-F3-H3 -> 0
A4: 46268 | B4: Thu | C4: =Summary!C6 -> 0 | D4: =Summary!U6 -> 0 | G4: =C4+D4 -> 0 | I4: =I3+G4+E4-F4-H4 -> 0
A5: 46269 | B5: Fri | C5: =Summary!C7 -> 0 | D5: =Summary!U7 -> 0 | G5: =C5+D5 -> 0 | I5: =I4+G5+E5-F5-H5 -> 0
A6: 46270 | B6: Sat | C6: =Summary!C8 -> 0 | D6: =Summary!U8 -> 0 | G6: =C6+D6 -> 0 | I6: =I5+G6+E6-F6-H6 -> 0
A7: 46271 | B7: Sun | C7: =Summary!C9 -> 0 | D7: =Summary!U9 -> 0 | G7: =C7+D7 -> 0 | I7: =I6+G7+E7-F7-H7 -> 0
A8: 46272 | B8: Mon | C8: =Summary!C10 -> 0 | D8: =Summary!U10 -> 0 | G8: =C8+D8 -> 0 | I8: =I7+G8+E8-F8-H8 -> 0
A9: 46273 | B9: Tue | C9: =Summary!C11 -> 0 | D9: =Summary!U11 -> 0 | G9: =C9+D9 -> 0 | I9: =I8+G9+E9-F9-H9 -> 0
A10: 46274 | B10: Wed | C10: =Summary!C12 -> 0 | D10: =Summary!U12 -> 0 | G10: =C10+D10 -> 0 | I10: =I9+G10+E10-F10-H10 -> 0
A11: 46275 | B11: Thu | C11: =Summary!C13 -> 0 | D11: =Summary!U13 -> 0 | G11: =C11+D11 -> 0 | I11: =I10+G11+E11-F11-H11 -> 0
A12: 46276 | B12: Fri | C12: =Summary!C14 -> 0 | D12: =Summary!U14 -> 0 | G12: =C12+D12 -> 0 | I12: =I11+G12+E12-F12-H12 -> 0
A13: 46277 | B13: Sat | C13: =Summary!C15 -> 0 | D13: =Summary!U15 -> 0 | G13: =C13+D13 -> 0 | I13: =I12+G13+E13-F13-H13 -> 0
A14: 46278 | B14: Sun | C14: =Summary!C16 -> 0 | D14: =Summary!U16 -> 0 | G14: =C14+D14 -> 0 | I14: =I13+G14+E14-F14-H14 -> 0
... A32: 46265 | B32: Mon | C32: =Summary!C34 -> 0 | D32: =Summary!U34 -> 0 | G32: =C32+D32 -> 0 | I32: =I31+G32+E32-F32-H32 -> 0
C34: =SUM(C2:C32) -> 0 | D34: =SUM(D2:D32) -> 0 | E34: =SUM(E2:E32) -> 0 | F34: =SUM(F2:F32) -> 0 | G34: =SUM(G2:G32) -> 0 | H34: =SUM(H2:H32) -> 0 | I34: =SUM(I2:I32) -> 0
